langhook/__init__.py
langhook/app.py
langhook/client.py
langhook/main.py
langhook/cli/__init__.py
langhook/cli/dlq_show.py
langhook/cli/stream_manager.py
langhook/cli/topic_manager.py
langhook/core/__init__.py
langhook/core/config.py
langhook/core/fastapi.py
langhook/core/kafka.py
langhook/core/nats.py
langhook/core/startup.py
langhook/ingest/__init__.py
langhook/ingest/config.py
langhook/ingest/kafka.py
langhook/ingest/middleware.py
langhook/ingest/nats.py
langhook/ingest/security.py
langhook/map/__init__.py
langhook/map/cloudevents.py
langhook/map/config.py
langhook/map/fingerprint.py
langhook/map/kafka.py
langhook/map/llm.py
langhook/map/llm.py.backup
langhook/map/mapper.py
langhook/map/metrics.py
langhook/map/nats.py
langhook/map/service.py
langhook/router/__init__.py
langhook/router/config.py
langhook/subscriptions/__init__.py
langhook/subscriptions/config.py
langhook/subscriptions/consumer_service.py
langhook/subscriptions/database.py
langhook/subscriptions/dlq_logging.py
langhook/subscriptions/event_logging.py
langhook/subscriptions/gate.py
langhook/subscriptions/llm.py
langhook/subscriptions/models.py
langhook/subscriptions/prompts.py
langhook/subscriptions/routes.py
langhook/subscriptions/schema_registry.py
langhook/subscriptions/schema_routes.py
langhook/subscriptions/schemas.py
langhook/static/asset-manifest.json
langhook/static/index.html
langhook/static/static/css/main.1befcbf7.css
langhook/static/static/css/main.1befcbf7.css.map
langhook/static/static/js/main.f8153e0a.js
langhook/static/static/js/main.f8153e0a.js.LICENSE.txt
langhook/static/static/js/main.f8153e0a.js.map
langhook-0.3.28.dist-info/METADATA
langhook-0.3.28.dist-info/WHEEL
langhook-0.3.28.dist-info/entry_points.txt
langhook-0.3.28.dist-info/licenses/LICENSE
langhook-0.3.28.dist-info/RECORD
