Metadata-Version: 2.4
Name: langhook
Version: 0.3.28
Summary: LangHook Python SDK and Server - Make any event from anywhere instantly understandable and actionable by anyone
Project-URL: Homepage, https://github.com/convolabai/langhook
Project-URL: Repository, https://github.com/convolabai/langhook
Project-URL: Issues, https://github.com/convolabai/langhook/issues
Author-email: LangHook Team <team@langhook.dev>
License: MIT License
License-File: LICENSE
Classifier: Development Status :: 3 - Alpha
Classifier: Intended Audience :: Developers
Classifier: License :: OSI Approved :: MIT License
Classifier: Programming Language :: Python :: 3
Classifier: Programming Language :: Python :: 3.12
Classifier: Topic :: Internet :: WWW/HTTP :: HTTP Servers
Classifier: Topic :: Software Development :: Libraries :: Application Frameworks
Requires-Python: >=3.12
Requires-Dist: httpx>=0.24.0
Requires-Dist: pydantic>=2.0.0
Provides-Extra: dev
Requires-Dist: build; extra == 'dev'
Requires-Dist: httpx>=0.24.0; extra == 'dev'
Requires-Dist: mypy>=1.5.0; extra == 'dev'
Requires-Dist: pytest-asyncio>=0.21.0; extra == 'dev'
Requires-Dist: pytest-mock>=3.10.0; extra == 'dev'
Requires-Dist: pytest>=7.0.0; extra == 'dev'
Requires-Dist: ruff>=0.1.0; extra == 'dev'
Provides-Extra: server
Requires-Dist: cloudevents>=1.11.0; extra == 'server'
Requires-Dist: fastapi>=0.111.0; extra == 'server'
Requires-Dist: jsonata>=0.2.0; extra == 'server'
Requires-Dist: jsonschema>=4.0.0; extra == 'server'
Requires-Dist: langchain-openai>=0.2.0; extra == 'server'
Requires-Dist: langchain>=0.1.0; extra == 'server'
Requires-Dist: nats-py>=2.9.0; extra == 'server'
Requires-Dist: openai>=1.0.0; extra == 'server'
Requires-Dist: prometheus-client>=0.16.0; extra == 'server'
Requires-Dist: psycopg2-binary>=2.9.0; extra == 'server'
Requires-Dist: python-dotenv>=1.1.0; extra == 'server'
Requires-Dist: pyyaml>=6.0; extra == 'server'
Requires-Dist: redis[hiredis]>=5.0.0; extra == 'server'
Requires-Dist: sqlalchemy>=2.0.0; extra == 'server'
Requires-Dist: structlog>=23.0.0; extra == 'server'
Requires-Dist: uvicorn[standard]>=0.29.0; extra == 'server'
